RISC-V I 32bit single cycled processor/RTL/pc.v
module pc(
input clk,
input reset,
input [31:0] pc_in,
output reg [31:0] pc_out
);
always @(posedge clk or posedge reset) begin
     if (reset) begin
        pc_out<=32'd0;
     end else begin 
        pc_out<=pc_in;
     end
end

endmodule

RISC-V I 32bit single cycled processor/Testbench/pc_tb.v
`timescale 1ns/1ps
module pc_tb;
reg clk;
reg reset;
reg [31:0] pc_in;
wire [31:0] pc_out;
pc uut(
.clk(clk),
.reset(rest),
.pc_in(pc_in),
.pc_out(pc_out)
);
always #5 clk=~clk;
initial begin 
    $dumpfile("pc.vcd");
    $dumpvars(0,pc_tb);
         clk = 0;
        reset = 1; // Assert reset initially
        pc_in = 32'd0;
        #10;

        // Release reset
        reset = 0;
        #10;

        // Simulate PC + 4 increments
        pc_in = 32'd4;   // PC = 4
        #10;

        pc_in = 32'd8;   // PC = 8
        #10;

        pc_in = 32'd12;  // PC = 12
        #10;

        // Test Reset during operation
        reset = 1;
        #10;

        reset = 0;
        pc_in = 32'd4;
        #10;

        $finish;
    end

endmodule

RISC-V I 32bit single cycled processor/SIM/pc_tb.vcd
$date
	Mon Sep 21 03:34:54 2026
$end
$version
	Icarus Verilog
$end
$timescale
	1ps
$end
$scope module pc_tb $end
$var wire 1 ! rest $end
$var wire 32 " pc_out [31:0] $end
$var reg 1 # clk $end
$var reg 32 $ pc_in [31:0] $end
$var reg 1 % reset $end
$scope module uut $end
$var wire 1 # clk $end
$var wire 32 & pc_in [31:0] $end
$var wire 1 ! reset $end
$var reg 32 ' pc_out [31:0] $end
$upscope $end
$upscope $end
$enddefinitions $end
$comment Show the parameter values. $end
$dumpall
$end
#0
$dumpvars
bx '
b0 &
1%
b0 $
0#
bx "
z!
$end
#5000
b0 "
b0 '
1#
#10000
0#
0%
#15000
1#
#20000
0#
b100 $
b100 &
#25000
b100 "
b100 '
1#
#30000
0#
b1000 $
b1000 &
#35000
b1000 "
b1000 '
1#
#40000
0#
b1100 $
b1100 &
#45000
b1100 "
b1100 '
1#
#50000
0#
1%
#55000
1#
#60000
0#
b100 $
b100 &
0%
#65000
b100 "
b100 '
1#
